<Tournament><name>第五十三回定例大会</name>
<Participant><id>1</id>
<name>shinonome</name>
<Deck>幽々子4</Deck>
<isHostable>false</isHostable>
</Participant>
<Participant><id>2</id>
<name>Urakagi</name>
<Deck>諏訪子3：神奈子1</Deck>
<isHostable>true</isHostable>
</Participant>
<Participant><id>3</id>
<name>seppei</name>
<Deck>藍2：紫2</Deck>
<isHostable>false</isHostable>
</Participant>
<Participant><id>4</id>
<name>namibianoizumi</name>
<Deck>慧音2：レミリア1：萃香1</Deck>
<isHostable>false</isHostable>
</Participant>
<Participant><id>5</id>
<name>kin</name>
<Deck>妖夢1：レミリア3</Deck>
<isHostable>true</isHostable>
</Participant>
<Participant><id>6</id>
<name>nanasuke</name>
<Deck>諏訪子3：神奈子1</Deck>
<isHostable>true</isHostable>
</Participant>
<Participant><id>7</id>
<name>daiki</name>
<Deck>にとり2：文2</Deck>
<isHostable>true</isHostable>
</Participant>
<Participant><id>8</id>
<name>shino</name>
<Deck>レミリア4</Deck>
<isHostable>true</isHostable>
</Participant>
<Participant><id>9</id>
<name>otamon</name>
<Deck>文1：レミリア1：幽々子1：パチュリー1</Deck>
<isHostable>false</isHostable>
</Participant>
<Participant><id>10</id>
<name>puttyo-</name>
<Deck>諏訪子3：神奈子1</Deck>
<isHostable>false</isHostable>
</Participant>
<Participant><id>11</id>
<name>t_mikage</name>
<Deck>魔理沙3：パチュリー1</Deck>
<isHostable>false</isHostable>
</Participant>
<Participant><id>12</id>
<name>Arrow</name>
<Deck>小町1：咲夜1：妖夢1：美鈴1</Deck>
<isHostable>true</isHostable>
</Participant>
<Participant><id>13</id>
<name>gidadan</name>
<Deck>輝夜3：レミリア1</Deck>
<isHostable>false</isHostable>
</Participant>
<Participant><id>14</id>
<name>Chabu-</name>
<Deck>文3：早苗1</Deck>
<isHostable>true</isHostable>
</Participant>
<Participant><id>15</id>
<name>kotti2</name>
<Deck>紫1：美鈴2：小町1</Deck>
<isHostable>true</isHostable>
</Participant>
<Participant><id>17</id>
<name>YanMon</name>
<Deck>妖夢2：咲夜1：鈴仙1</Deck>
<isHostable>true</isHostable>
</Participant>
<Participant><id>16</id>
<name>keychi</name>
<Deck>霊夢3：咲夜1</Deck>
<isHostable>true</isHostable>
</Participant>
<Participant><id>19</id>
<name>Kouun</name>
<Deck>にとり4</Deck>
<isHostable>true</isHostable>
</Participant>
<Participant><id>18</id>
<name>snorri</name>
<Deck>紫1：魔理沙3</Deck>
<isHostable>false</isHostable>
</Participant>
<Participant><id>21</id>
<name>yuki2</name>
<Deck>レミリア2：魔理沙2</Deck>
<isHostable>true</isHostable>
</Participant>
<Participant><id>20</id>
<name>CJ</name>
<Deck>アリス2：美鈴2</Deck>
<isHostable>true</isHostable>
</Participant>
<Participant><id>23</id>
<name>Spirit_K</name>
<Deck>妖夢1：フランドール3</Deck>
<isHostable>true</isHostable>
</Participant>
<Participant><id>22</id>
<name>F</name>
<Deck>魔理沙1：霊夢1：萃香1：神奈子1</Deck>
<isHostable>true</isHostable>
</Participant>
<Participant><id>25</id>
<name>myoga</name>
<Deck>萃香3：早苗1</Deck>
<isHostable>false</isHostable>
</Participant>
<Participant><id>24</id>
<name>krast_D</name>
<Deck>レミリア2：咲夜1：パチュリー1</Deck>
<isHostable>false</isHostable>
</Participant>
<Participant><id>27</id>
<name>tenjoin</name>
<Deck>永琳3：輝夜1</Deck>
<isHostable>true</isHostable>
</Participant>
<Participant><id>26</id>
<name>Koakuma</name>
<Deck>霊夢4</Deck>
<isHostable>true</isHostable>
</Participant>
<Participant><id>28</id>
<name>Aonami</name>
<Deck>パチュリー3：霊夢1</Deck>
<isHostable>true</isHostable>
</Participant>
<Round><id>1</id>
<Table><Player>krast_D</Player>
<Player>kin</Player>
<Winner>kin</Winner>
</Table>
<Table><Player>gidadan</Player>
<Player>daiki</Player>
<Winner>daiki</Winner>
</Table>
<Table><Player>Kouun</Player>
<Player>t_mikage</Player>
<Winner>Kouun</Winner>
</Table>
<Table><Player>shinonome</Player>
<Player>Spirit_K</Player>
<Winner>Spirit_K</Winner>
</Table>
<Table><Player>snorri</Player>
<Player>Aonami</Player>
<Winner>snorri</Winner>
</Table>
<Table><Player>Arrow</Player>
<Player>seppei</Player>
<Winner>Arrow</Winner>
</Table>
<Table><Player>Koakuma</Player>
<Player>Chabu-</Player>
<Winner>Koakuma</Winner>
</Table>
<Table><Player>CJ</Player>
<Player>otamon</Player>
<Winner>CJ</Winner>
</Table>
<Table><Player>tenjoin</Player>
<Player>puttyo-</Player>
<Winner>tenjoin</Winner>
</Table>
<Table><Player>nanasuke</Player>
<Player>shino</Player>
<Winner>shino</Winner>
</Table>
<Table><Player>kotti2</Player>
<Player>namibianoizumi</Player>
<Winner>kotti2</Winner>
</Table>
<Table><Player>keychi</Player>
<Player>F</Player>
<Winner>keychi</Winner>
</Table>
<Table><Player>yuki2</Player>
<Player>myoga</Player>
<Winner>myoga</Winner>
</Table>
<Table><Player>Urakagi</Player>
<Player>YanMon</Player>
<Winner>Urakagi</Winner>
</Table>
</Round>
<Round><id>2</id>
<Table><Player>daiki</Player>
<Player>snorri</Player>
<Winner>snorri</Winner>
</Table>
<Table><Player>Spirit_K</Player>
<Player>Koakuma</Player>
<Winner>Koakuma</Winner>
</Table>
<Table><Player>Urakagi</Player>
<Player>keychi</Player>
<Winner>Urakagi</Winner>
</Table>
<Table><Player>tenjoin</Player>
<Player>Arrow</Player>
<Winner>tenjoin</Winner>
</Table>
<Table><Player>shino</Player>
<Player>kotti2</Player>
<Winner>kotti2</Winner>
</Table>
<Table><Player>CJ</Player>
<Player>kin</Player>
<Winner>CJ</Winner>
</Table>
<Table><Player>Kouun</Player>
<Player>myoga</Player>
<Winner>Kouun</Winner>
</Table>
<Table><Player>YanMon</Player>
<Player>otamon</Player>
<Winner>YanMon</Winner>
</Table>
<Table><Player>shinonome</Player>
<Player>Chabu-</Player>
<Winner>shinonome</Winner>
</Table>
<Table><Player>seppei</Player>
<Player>F</Player>
<Winner>F</Winner>
</Table>
<Table><Player>Aonami</Player>
<Player>namibianoizumi</Player>
<Winner>namibianoizumi</Winner>
</Table>
<Table><Player>krast_D</Player>
<Player>nanasuke</Player>
<Winner>krast_D</Winner>
</Table>
<Table><Player>t_mikage</Player>
<Player>yuki2</Player>
<Winner>t_mikage</Winner>
</Table>
<Table><Player>puttyo-</Player>
<Player>gidadan</Player>
<Winner>puttyo-</Winner>
</Table>
</Round>
<Round><id>3</id>
<Table><Player>Kouun</Player>
<Player>kotti2</Player>
<Winner>Kouun</Winner>
</Table>
<Table><Player>CJ</Player>
<Player>snorri</Player>
<Winner>CJ</Winner>
</Table>
<Table><Player>Koakuma</Player>
<Player>Urakagi</Player>
<Winner>Urakagi</Winner>
</Table>
<Table><Player>tenjoin</Player>
<Player>daiki</Player>
<Winner>daiki</Winner>
</Table>
<Table><Player>YanMon</Player>
<Player>keychi</Player>
<Winner>YanMon</Winner>
</Table>
<Table><Player>Spirit_K</Player>
<Player>F</Player>
<Winner>F</Winner>
</Table>
<Table><Player>t_mikage</Player>
<Player>Arrow</Player>
<Winner>t_mikage</Winner>
</Table>
<Table><Player>myoga</Player>
<Player>shino</Player>
<Winner>shino</Winner>
</Table>
<Table><Player>kin</Player>
<Player>puttyo-</Player>
<Winner>kin</Winner>
</Table>
<Table><Player>namibianoizumi</Player>
<Player>shinonome</Player>
<Winner>shinonome</Winner>
</Table>
<Table><Player>krast_D</Player>
<Player>Aonami</Player>
<Winner>Aonami</Winner>
</Table>
<Table><Player>gidadan</Player>
<Player>Chabu-</Player>
<Winner>Chabu-</Winner>
</Table>
<Table><Player>otamon</Player>
<Player>nanasuke</Player>
<Winner>nanasuke</Winner>
</Table>
<Table><Player>yuki2</Player>
<Player>seppei</Player>
<Winner>seppei</Winner>
</Table>
</Round>
<Round><id>4</id>
<Table><Player>Kouun</Player>
<Player>Urakagi</Player>
<Winner>Kouun</Winner>
</Table>
<Table><Player>CJ</Player>
<Player>t_mikage</Player>
<Winner>t_mikage</Winner>
</Table>
<Table><Player>snorri</Player>
<Player>tenjoin</Player>
<Winner>tenjoin</Winner>
</Table>
<Table><Player>shinonome</Player>
<Player>Koakuma</Player>
<Winner>Koakuma</Winner>
</Table>
<Table><Player>kin</Player>
<Player>kotti2</Player>
<Winner>kotti2</Winner>
</Table>
<Table><Player>daiki</Player>
<Player>F</Player>
<Winner>F</Winner>
</Table>
<Table><Player>shino</Player>
<Player>YanMon</Player>
<Winner>shino</Winner>
</Table>
<Table><Player>Chabu-</Player>
<Player>Aonami</Player>
<Winner>Aonami</Winner>
</Table>
<Table><Player>krast_D</Player>
<Player>Arrow</Player>
<Winner>krast_D</Winner>
</Table>
<Table><Player>keychi</Player>
<Player>myoga</Player>
<Winner>keychi</Winner>
</Table>
<Table><Player>Spirit_K</Player>
<Player>namibianoizumi</Player>
<Winner>Spirit_K</Winner>
</Table>
<Table><Player>puttyo-</Player>
<Player>nanasuke</Player>
<Winner>puttyo-</Winner>
</Table>
<Table><Player>seppei</Player>
<Player>otamon</Player>
<Winner>seppei</Winner>
</Table>
<Table><Player>yuki2</Player>
<Player>gidadan</Player>
<Winner>gidadan</Winner>
</Table>
</Round>
</Tournament>
