<Tournament><name>第二十一回定例大会</name>
<Promoter></Promoter>
<date>0</date>
<Participant><id>1</id>
<name>Urakagi</name>
<Deck>藍1：妖夢1：紫1：橙1</Deck>
<isHostable>true</isHostable>
<IP></IP>
</Participant>
<Participant><id>2</id>
<name>untyosi</name>
<Deck>鈴仙3：フランドール1</Deck>
<isHostable>true</isHostable>
<IP></IP>
</Participant>
<Participant><id>3</id>
<name>krast_D</name>
<Deck>美鈴2：慧音1：萃香1</Deck>
<isHostable>true</isHostable>
<IP></IP>
</Participant>
<Participant><id>4</id>
<name>momyument</name>
<Deck>藍2：紫1：橙1</Deck>
<isHostable>true</isHostable>
<IP></IP>
</Participant>
<Participant><id>5</id>
<name>sechi</name>
<Deck>藍3：妖夢1</Deck>
<isHostable>true</isHostable>
<IP></IP>
</Participant>
<Participant><id>6</id>
<name>tsubame</name>
<Deck>フランドール3：レミリア1</Deck>
<isHostable>true</isHostable>
<IP></IP>
</Participant>
<Participant><id>7</id>
<name>kumatora</name>
<Deck>妖夢1：慧音3</Deck>
<isHostable>true</isHostable>
<IP></IP>
</Participant>
<Participant><id>8</id>
<name>Zone</name>
<Deck>慧音4</Deck>
<isHostable>true</isHostable>
<IP></IP>
</Participant>
<Participant><id>9</id>
<name>keychi</name>
<Deck>妹紅3：萃香1</Deck>
<isHostable>true</isHostable>
<IP></IP>
</Participant>
<Participant><id>10</id>
<name>F</name>
<Deck>レミリア4</Deck>
<isHostable>true</isHostable>
<IP></IP>
</Participant>
<Participant><id>11</id>
<name>alondite</name>
<Deck>妹紅4</Deck>
<isHostable>true</isHostable>
<IP></IP>
</Participant>
<Participant><id>12</id>
<name>bukkun</name>
<Deck>パチュリー3：霊夢1</Deck>
<isHostable>true</isHostable>
<IP></IP>
</Participant>
<Participant><id>13</id>
<name>Sait</name>
<Deck>紫1：幽々子1：藍1：橙1</Deck>
<isHostable>true</isHostable>
<IP></IP>
</Participant>
<Participant><id>14</id>
<name>Kb_aya</name>
<Deck>幽々子2：妖夢1：プリズムリバー1</Deck>
<isHostable>true</isHostable>
<IP></IP>
</Participant>
<Participant><id>15</id>
<name>uturogi</name>
<Deck>萃香4</Deck>
<isHostable>true</isHostable>
<IP></IP>
</Participant>
<Participant><id>17</id>
<name>tenjoin</name>
<Deck>萃香4</Deck>
<isHostable>true</isHostable>
<IP></IP>
</Participant>
<Participant><id>16</id>
<name>K2M2</name>
<Deck>咲夜1：魔理沙3</Deck>
<isHostable>true</isHostable>
<IP></IP>
</Participant>
<Participant><id>19</id>
<name>sakuyann</name>
<Deck>咲夜4</Deck>
<isHostable>true</isHostable>
<IP></IP>
</Participant>
<Participant><id>18</id>
<name>yatuhashi</name>
<Deck>パチュリー2：永琳2</Deck>
<isHostable>true</isHostable>
<IP></IP>
</Participant>
<Participant><id>21</id>
<name>cirno9</name>
<Deck>アリス3：橙1</Deck>
<isHostable>true</isHostable>
<IP></IP>
</Participant>
<Participant><id>20</id>
<name>tanatana8</name>
<Deck>美鈴4</Deck>
<isHostable>true</isHostable>
<IP></IP>
</Participant>
<Participant><id>23</id>
<name>Chabu</name>
<Deck>咲夜4</Deck>
<isHostable>true</isHostable>
<IP></IP>
</Participant>
<Participant><id>22</id>
<name>logX</name>
<Deck>アリス2：輝夜2</Deck>
<isHostable>true</isHostable>
<IP></IP>
</Participant>
<Participant><id>24</id>
<name>kouraku</name>
<Deck>妹紅4</Deck>
<isHostable>true</isHostable>
<IP></IP>
</Participant>
<Round><id>1</id>
<Table><Player>Chabu</Player>
<Player>uturogi</Player>
<Winner>uturogi</Winner>
</Table>
<Table><Player>Sait</Player>
<Player>untyosi</Player>
<Winner>untyosi</Winner>
</Table>
<Table><Player>tenjoin</Player>
<Player>logX</Player>
<Winner>tenjoin</Winner>
</Table>
<Table><Player>sechi</Player>
<Player>tanatana8</Player>
<Winner>sechi</Winner>
</Table>
<Table><Player>sakuyann</Player>
<Player>K2M2</Player>
<Winner>sakuyann</Winner>
</Table>
<Table><Player>Kb_aya</Player>
<Player>bukkun</Player>
<Winner>bukkun</Winner>
</Table>
<Table><Player>momyument</Player>
<Player>F</Player>
<Winner>momyument</Winner>
</Table>
<Table><Player>keychi</Player>
<Player>Zone</Player>
<Winner>keychi</Winner>
</Table>
<Table><Player>alondite</Player>
<Player>tsubame</Player>
<Winner>alondite</Winner>
</Table>
<Table><Player>kouraku</Player>
<Player>kumatora</Player>
<Winner>kumatora</Winner>
</Table>
<Table><Player>cirno9</Player>
<Player>krast_D</Player>
<Winner>krast_D</Winner>
</Table>
<Table><Player>yatuhashi</Player>
<Player>Urakagi</Player>
<Winner>Urakagi</Winner>
</Table>
</Round>
<Round><id>2</id>
<Table><Player>Chabu</Player>
<Player>tsubame</Player>
<Winner>tsubame</Winner>
</Table>
<Table><Player>sakuyann</Player>
<Player>tanatana8</Player>
<Winner>tanatana8</Winner>
</Table>
<Table><Player>alondite</Player>
<Player>Sait</Player>
<Winner>Sait</Winner>
</Table>
<Table><Player>Kb_aya</Player>
<Player>keychi</Player>
<Winner>Kb_aya</Winner>
</Table>
<Table><Player>uturogi</Player>
<Player>logX</Player>
<Winner>uturogi</Winner>
</Table>
<Table><Player>K2M2</Player>
<Player>tenjoin</Player>
<Winner>K2M2</Winner>
</Table>
<Table><Player>kumatora</Player>
<Player>untyosi</Player>
<Winner>untyosi</Winner>
</Table>
<Table><Player>kouraku</Player>
<Player>sechi</Player>
<Winner>sechi</Winner>
</Table>
<Table><Player>cirno9</Player>
<Player>yatuhashi</Player>
<Winner>yatuhashi</Winner>
</Table>
<Table><Player>F</Player>
<Player>Urakagi</Player>
<Winner>Urakagi</Winner>
</Table>
<Table><Player>momyument</Player>
<Player>krast_D</Player>
<Winner>krast_D</Winner>
</Table>
<Table><Player>bukkun</Player>
<Player>Zone</Player>
<Winner>Zone</Winner>
</Table>
</Round>
<Round><id>3</id>
<Table><Player>uturogi</Player>
<Player>untyosi</Player>
<Winner>untyosi</Winner>
</Table>
<Table><Player>sechi</Player>
<Player>Urakagi</Player>
<Winner>Urakagi</Winner>
</Table>
<Table><Player>krast_D</Player>
<Player>tsubame</Player>
<Winner>tsubame</Winner>
</Table>
<Table><Player>sakuyann</Player>
<Player>alondite</Player>
<Winner>alondite</Winner>
</Table>
<Table><Player>tanatana8</Player>
<Player>Sait</Player>
<Winner>Sait</Winner>
</Table>
<Table><Player>Kb_aya</Player>
<Player>K2M2</Player>
<Winner>Kb_aya</Winner>
</Table>
<Table><Player>keychi</Player>
<Player>tenjoin</Player>
<Winner>keychi</Winner>
</Table>
<Table><Player>kumatora</Player>
<Player>yatuhashi</Player>
<Winner>kumatora</Winner>
</Table>
<Table><Player>momyument</Player>
<Player>bukkun</Player>
<Winner>momyument</Winner>
</Table>
<Table><Player>Zone</Player>
<Player>Chabu</Player>
<Winner>Zone</Winner>
</Table>
<Table><Player>logX</Player>
<Player>kouraku</Player>
<Winner>logX</Winner>
</Table>
<Table><Player>cirno9</Player>
<Player>F</Player>
<Winner>F</Winner>
</Table>
</Round>
<Round><id>4</id>
<Table><Player>untyosi</Player>
<Player>Urakagi</Player>
<Winner>Urakagi</Winner>
</Table>
<Table><Player>uturogi</Player>
<Player>sechi</Player>
<Winner>sechi</Winner>
</Table>
<Table><Player>krast_D</Player>
<Player>alondite</Player>
<Winner>krast_D</Winner>
</Table>
<Table><Player>tsubame</Player>
<Player>Sait</Player>
<Winner>tsubame</Winner>
</Table>
<Table><Player>Kb_aya</Player>
<Player>kumatora</Player>
<Winner>kumatora</Winner>
</Table>
<Table><Player>keychi</Player>
<Player>momyument</Player>
<Winner>momyument</Winner>
</Table>
<Table><Player>Zone</Player>
<Player>sakuyann</Player>
<Winner>Zone</Winner>
</Table>
<Table><Player>tanatana8</Player>
<Player>K2M2</Player>
<Winner>K2M2</Winner>
</Table>
<Table><Player>tenjoin</Player>
<Player>yatuhashi</Player>
<Winner>tenjoin</Winner>
</Table>
<Table><Player>bukkun</Player>
<Player>logX</Player>
<Winner>bukkun</Winner>
</Table>
<Table><Player>F</Player>
<Player>Chabu</Player>
<Winner>F</Winner>
</Table>
<Table><Player>kouraku</Player>
<Player>cirno9</Player>
<Winner>cirno9</Winner>
</Table>
</Round>
</Tournament>
